{
    "has_more": false, 
    "message": "success", 
    "data": [
        {
            "image_url": "//p1.pstatp.com/list/pgc-image/bdd74214545f4514bb2b60b62ddbb150", 
            "single_mode": false, 
            "middle_mode": true, 
            "more_mode": false, 
            "tag": "news", 
            "chinese_tag": "其它", 
            "tag_url": "search/?keyword=%E5%85%B6%E5%AE%83", 
            "title": "河南许昌 郑许市域铁路加速“北进”计划于2020年建成投用", 
            "label": [
                "许昌", 
                "河南"
            ], 
            "source": "老牛视觉", 
            "group_source": 2, 
            "has_gallery": true, 
            "media_url": "/c/user/64373973446/", 
            "media_avatar_url": "//p5a.pstatp.com/large/ff6f0000078caf04d312", 
            "image_list": [
                {
                    "url": "//p1.pstatp.com/list/190x124/pgc-image/7f8628af3e3f4fecac6769bcd79ead45"
                }, 
                {
                    "url": "//p1.pstatp.com/list/190x124/pgc-image/5654ad5cec5d41d1b8791922097108bb"
                }, 
                {
                    "url": "//p3.pstatp.com/list/190x124/pgc-image/57f0e683e7204e4fb747c3882c81192c"
                }, 
                {
                    "url": "//p1.pstatp.com/list/190x124/pgc-image/bdd74214545f4514bb2b60b62ddbb150"
                }
            ], 
            "gallary_image_count": 4, 
            "source_url": "/group/6671879640216240651/", 
            "article_genre": "gallery", 
            "item_id": "6671879640216240651", 
            "is_feed_ad": false, 
            "gallary_flag": 1, 
            "behot_time": 1553789412, 
            "comments_count": 30, 
            "group_id": "6671879640216240651", 
            "middle_image": "http://p1.pstatp.com/list/pgc-image/bdd74214545f4514bb2b60b62ddbb150"
        }, 
        {
            "image_url": "//p3.pstatp.com/list/pgc-image/cbe938236a4c401ba209e1ac36baea4a", 
            "single_mode": false, 
            "middle_mode": true, 
            "more_mode": true, 
            "tag": "news_entertainment", 
            "chinese_tag": "娱乐", 
            "tag_url": "news_entertainment", 
            "title": "盘点9位香港明星年轻照，这组照片能认全的，说明你真的老了", 
            "label": [
                "歌手", 
                "林青霞", 
                "成龙", 
                "徐克", 
                "香港", 
                "林子祥", 
                "许冠杰", 
                "洪金宝", 
                "狄龙", 
                "刘德华"
            ], 
            "source": "手机摄影周刊", 
            "group_source": 2, 
            "has_gallery": true, 
            "media_url": "/c/user/3642193731/", 
            "media_avatar_url": "//p8.pstatp.com/large/2c5f0008506345dba529", 
            "image_list": [
                {
                    "url": "//p3.pstatp.com/list/190x124/pgc-image/cbe938236a4c401ba209e1ac36baea4a"
                }, 
                {
                    "url": "//p3.pstatp.com/list/190x124/pgc-image/167dbbbc011a47e2a3dbc8e34afb4cc0"
                }, 
                {
                    "url": "//p3.pstatp.com/list/190x124/pgc-image/268775b7f8644879aea01c718a6befc7"
                }, 
                {
                    "url": "//p1.pstatp.com/list/190x124/pgc-image/278b751ae7c24d2daed1dc4d81497327"
                }
            ], 
            "gallary_image_count": 9, 
            "source_url": "/group/6673433978596229636/", 
            "article_genre": "gallery", 
            "item_id": "6673433978596229636", 
            "is_feed_ad": false, 
            "gallary_flag": 3, 
            "behot_time": 1553789410, 
            "comments_count": 7, 
            "group_id": "6673433978596229636", 
            "middle_image": "http://p3.pstatp.com/list/pgc-image/cbe938236a4c401ba209e1ac36baea4a"
        }, 
        {
            "image_url": "//p3.pstatp.com/list/pgc-image/e9d5a4840e6c4a70a8c665f9278760f7", 
            "single_mode": false, 
            "middle_mode": true, 
            "more_mode": true, 
            "tag": "news_traditional_culture", 
            "tag_url": "search/?keyword=None", 
            "title": "魏碑经典系列 《郑文公碑上》 一", 
            "label": [
                "郑文公", 
                "郑道昭", 
                "魏宣武帝", 
                "南阳", 
                "北魏", 
                "清朝", 
                "包世臣", 
                "莱州", 
                "书法", 
                "天柱山", 
                "阮元", 
                "山东", 
                "政和", 
                "康有为", 
                "平度", 
                "荥阳", 
                "叶昌炽", 
                "宋朝", 
                "文物"
            ], 
            "source": "书画博物馆", 
            "group_source": 2, 
            "has_gallery": true, 
            "media_url": "/c/user/17464147298/", 
            "media_avatar_url": "//p1.pstatp.com/large/dc0c00056b912bab08ce", 
            "image_list": [
                {
                    "url": "//p3.pstatp.com/list/190x124/pgc-image/e9d5a4840e6c4a70a8c665f9278760f7"
                }, 
                {
                    "url": "//p1.pstatp.com/list/190x124/pgc-image/18605f449f7b4590a27b3da4672a4d27"
                }, 
                {
                    "url": "//p1.pstatp.com/list/190x124/pgc-image/09f93bd5f29b478092730e3b7572a88f"
                }, 
                {
                    "url": "//p1.pstatp.com/list/190x124/pgc-image/357fc2c264b64f6cb340cc46ed11b19c"
                }
            ], 
            "gallary_image_count": 25, 
            "source_url": "/group/6673259925419852301/", 
            "article_genre": "gallery", 
            "item_id": "6673259925419852301", 
            "is_feed_ad": false, 
            "gallary_flag": 1, 
            "behot_time": 1553789409, 
            "comments_count": 10, 
            "group_id": "6673259925419852301", 
            "middle_image": "http://p3.pstatp.com/list/pgc-image/e9d5a4840e6c4a70a8c665f9278760f7"
        }, 
        {
            "image_url": "//p1.pstatp.com/list/pgc-image/803cbdbd486e49888bf9057d284f4fa2", 
            "single_mode": false, 
            "middle_mode": true, 
            "more_mode": true, 
            "tag": "news_entertainment", 
            "chinese_tag": "娱乐", 
            "tag_url": "news_entertainment", 
            "title": "人物影像：王丽坤，出生于内蒙古赤峰市，一次回眸而被徐克选中", 
            "label": [
                "王丽坤", 
                "内蒙古", 
                "徐克", 
                "赤峰", 
                "电视剧", 
                "北京舞蹈学院", 
                "北京大学生电影节", 
                "翁牛特", 
                "弱关联—清宫Q传", 
                "美人心计", 
                "七剑下天山", 
                "喜剧电影", 
                "西游伏妖篇", 
                "国剧盛典", 
                "江苏", 
                "大学", 
                "江苏卫视", 
                "电影节", 
                "有一个地方只有我们知道", 
                "爱的多米诺", 
                "八十一格", 
                "五号特工组"
            ], 
            "source": "宋渭涛骊泉影像", 
            "group_source": 2, 
            "has_gallery": true, 
            "media_url": "/c/user/51511128471/", 
            "media_avatar_url": "//p2.pstatp.com/large/933100048c13073e184e", 
            "image_list": [
                {
                    "url": "//p1.pstatp.com/list/190x124/pgc-image/803cbdbd486e49888bf9057d284f4fa2"
                }, 
                {
                    "url": "//p1.pstatp.com/list/190x124/pgc-image/0451b35cad2b4ef798b51f122875457e"
                }, 
                {
                    "url": "//p9.pstatp.com/list/190x124/pgc-image/f7a934f9f0ee41faa057c9baa3851713"
                }, 
                {
                    "url": "//p3.pstatp.com/list/190x124/pgc-image/5f0ce9c51c19457f8d6590791234462b"
                }
            ], 
            "gallary_image_count": 13, 
            "source_url": "/group/6672862160558752260/", 
            "article_genre": "gallery", 
            "item_id": "6672862160558752260", 
            "is_feed_ad": false, 
            "gallary_flag": 1, 
            "behot_time": 1553789408, 
            "comments_count": 46, 
            "group_id": "6672862160558752260", 
            "middle_image": "http://p1.pstatp.com/list/pgc-image/803cbdbd486e49888bf9057d284f4fa2"
        }, 
        {
            "single_mode": false, 
            "middle_mode": true, 
            "more_mode": false, 
            "tag": "news_fashion", 
            "label": [
                "时尚", 
                "服装", 
                "设计"
            ], 
            "tag_url": "news_fashion", 
            "title": "百搭的时尚外套，爱美的你不可错过，哦！", 
            "chinese_tag": "时尚", 
            "source": "调皮捣蛋的鱼鱼", 
            "group_source": 2, 
            "image_url": "//p3.pstatp.com/list/pgc-image/4982e7c8331f4b829b64a046d4c2d790", 
            "media_url": "/c/user/109415042466/", 
            "media_avatar_url": "//p5a.pstatp.com/large/ff3e0000299e26b762f1", 
            "image_list": [
                {
                    "url": "//p3.pstatp.com/list/190x124/pgc-image/8e5cf5a4d0694eb8bec0ff1c7fd2c217"
                }, 
                {
                    "url": "//p3.pstatp.com/list/190x124/pgc-image/7d1111266b4c41dfa97e78e1da8a3a8d"
                }, 
                {
                    "url": "//p1.pstatp.com/list/190x124/pgc-image/e72e1daa185f47258cd29b97a3948f5b"
                }, 
                {
                    "url": "//p9.pstatp.com/list/190x124/pgc-image/b7f5b3bfdc464126a485930bc1d60bd1"
                }
            ], 
            "gallary_image_count": 8, 
            "source_url": "/group/6673241410545648141/", 
            "article_genre": "gallery", 
            "item_id": "6673241410545648141", 
            "is_feed_ad": false, 
            "gallary_flag": 1, 
            "behot_time": 1553789406, 
            "has_gallery": true, 
            "group_id": "6673241410545648141", 
            "middle_image": "http://p3.pstatp.com/list/pgc-image/4982e7c8331f4b829b64a046d4c2d790"
        }, 
        {
            "image_url": "//p1.pstatp.com/list/pgc-image/6bc1832e177443619dd8e24c0b2fe5bc", 
            "single_mode": false, 
            "middle_mode": true, 
            "more_mode": true, 
            "tag": "news_travel", 
            "chinese_tag": "旅游", 
            "tag_url": "news_travel", 
            "title": "建一座诗一样的山庄，益阳安化父子这样释解乡愁", 
            "label": [
                "安化", 
                "益阳", 
                "春节家书", 
                "美女", 
                "设计", 
                "设计师"
            ], 
            "source": "丰言疯語", 
            "group_source": 2, 
            "has_gallery": true, 
            "media_url": "/c/user/57828528478/", 
            "media_avatar_url": "//p6.pstatp.com/large/173b3001d0dbbb339a6e9", 
            "image_list": [
                {
                    "url": "//p1.pstatp.com/list/190x124/pgc-image/6bc1832e177443619dd8e24c0b2fe5bc"
                }, 
                {
                    "url": "//p1.pstatp.com/list/190x124/pgc-image/8e8d81f43c5d4462979c78b65d051fe3"
                }, 
                {
                    "url": "//p3.pstatp.com/list/190x124/pgc-image/55423c124a4349689db03fcf5e2d90e9"
                }, 
                {
                    "url": "//p1.pstatp.com/list/190x124/pgc-image/5c0769b4bede4d7891b2bcc4591cc76e"
                }
            ], 
            "gallary_image_count": 13, 
            "source_url": "/group/6673316113771659787/", 
            "article_genre": "gallery", 
            "item_id": "6673316113771659787", 
            "is_feed_ad": false, 
            "gallary_flag": 2, 
            "behot_time": 1553789405, 
            "comments_count": 9, 
            "group_id": "6673316113771659787", 
            "middle_image": "http://p1.pstatp.com/list/pgc-image/6bc1832e177443619dd8e24c0b2fe5bc"
        }, 
        {
            "image_url": "//p1.pstatp.com/list/pgc-image/3f88b908c3d3406cb32a87d2e2efd7bf", 
            "single_mode": false, 
            "middle_mode": true, 
            "more_mode": true, 
            "tag": "news_edu", 
            "chinese_tag": "教育", 
            "tag_url": "search/?keyword=%E6%95%99%E8%82%B2", 
            "title": "河北这所高校是应急管理部直属高校！原国家煤炭工业部投资兴建", 
            "label": [
                "河北", 
                "投资", 
                "煤炭", 
                "经济", 
                "技术", 
                "工程师", 
                "数据库", 
                "艺术", 
                "建筑"
            ], 
            "source": "小汪Doran校园资讯", 
            "group_source": 2, 
            "has_gallery": true, 
            "media_url": "/c/user/62886855916/", 
            "media_avatar_url": "//p10.pstatp.com/large/dabe0009a56fff5d2950", 
            "image_list": [
                {
                    "url": "//p1.pstatp.com/list/190x124/pgc-image/3f88b908c3d3406cb32a87d2e2efd7bf"
                }, 
                {
                    "url": "//p1.pstatp.com/list/190x124/pgc-image/dae4cc936b344072885ed7d46981b1a6"
                }, 
                {
                    "url": "//p3.pstatp.com/list/190x124/pgc-image/73f77fb249d54adb864f94e09b5a8cee"
                }, 
                {
                    "url": "//p3.pstatp.com/list/190x124/pgc-image/4ad25c74552a4af58490e59fef3e9c77"
                }
            ], 
            "gallary_image_count": 5, 
            "source_url": "/group/6673415491115024903/", 
            "article_genre": "gallery", 
            "item_id": "6673415491115024903", 
            "is_feed_ad": false, 
            "gallary_flag": 3, 
            "behot_time": 1553789404, 
            "comments_count": 4, 
            "group_id": "6673415491115024903", 
            "middle_image": "http://p1.pstatp.com/list/pgc-image/3f88b908c3d3406cb32a87d2e2efd7bf"
        }, 
        {
            "image_url": "//p9.pstatp.com/list/pgc-image/f98f5d058eee4c38849f7fe29ba5e2c3", 
            "single_mode": false, 
            "middle_mode": true, 
            "more_mode": true, 
            "tag": "news", 
            "chinese_tag": "其它", 
            "tag_url": "search/?keyword=%E5%85%B6%E5%AE%83", 
            "title": "兰州黄河风情线这个“连体”建筑是一大亮点  实拍项目近景效果好", 
            "label": [
                "兰州", 
                "黄河", 
                "兰州黄河", 
                "建筑", 
                "金·凯瑞"
            ], 
            "source": "兰州方程式", 
            "group_source": 2, 
            "has_gallery": true, 
            "media_url": "/c/user/5806204442/", 
            "media_avatar_url": "//p2.pstatp.com/large/10330/6971741856", 
            "image_list": [
                {
                    "url": "//p9.pstatp.com/list/190x124/pgc-image/f98f5d058eee4c38849f7fe29ba5e2c3"
                }, 
                {
                    "url": "//p1.pstatp.com/list/190x124/pgc-image/7c66559c612248989f52733c0dbd60a6"
                }, 
                {
                    "url": "//p3.pstatp.com/list/190x124/pgc-image/21ae0cf0a6d846cdac50e44e7e98ae35"
                }, 
                {
                    "url": "//p3.pstatp.com/list/190x124/pgc-image/21ae0cf0a6d846cdac50e44e7e98ae35"
                }
            ], 
            "gallary_image_count": 4, 
            "source_url": "/group/6673394110943986187/", 
            "article_genre": "gallery", 
            "item_id": "6673394110943986187", 
            "is_feed_ad": false, 
            "gallary_flag": 3, 
            "behot_time": 1553789402, 
            "comments_count": 1, 
            "group_id": "6673394110943986187", 
            "middle_image": "http://p9.pstatp.com/list/pgc-image/f98f5d058eee4c38849f7fe29ba5e2c3"
        }, 
        {
            "image_url": "//p9.pstatp.com/list/pgc-image/0ce0d5d24e5c459ca838f5874a02f5e2", 
            "single_mode": false, 
            "middle_mode": true, 
            "more_mode": true, 
            "tag": "news", 
            "chinese_tag": "其它", 
            "tag_url": "search/?keyword=%E5%85%B6%E5%AE%83", 
            "title": "福建离省会福州最远的县，素称“漳南第一关”！", 
            "label": [
                "福建", 
                "诏安", 
                "福州", 
                "浩瀚", 
                "艺术", 
                "漳州", 
                "汕头", 
                "历史", 
                "宁静", 
                "建筑", 
                "黄道周", 
                "文化", 
                "张大千", 
                "朱熹"
            ], 
            "source": "龙山户外驴友之家", 
            "group_source": 2, 
            "has_gallery": true, 
            "media_url": "/c/user/63966785116/", 
            "media_avatar_url": "//p3.pstatp.com/large/2c6e00123ed499f07a7b", 
            "image_list": [
                {
                    "url": "//p9.pstatp.com/list/190x124/pgc-image/0ce0d5d24e5c459ca838f5874a02f5e2"
                }, 
                {
                    "url": "//p3.pstatp.com/list/190x124/pgc-image/7922bdc49a0d47288828268cdfe10f75"
                }, 
                {
                    "url": "//p3.pstatp.com/list/190x124/pgc-image/2b63af69855f4830a35ee738b4abaaac"
                }, 
                {
                    "url": "//p1.pstatp.com/list/190x124/pgc-image/18192485e10b4ed89ab7f9dc36291f0a"
                }
            ], 
            "gallary_image_count": 8, 
            "source_url": "/group/6654506099221201420/", 
            "article_genre": "gallery", 
            "item_id": "6654506099221201420", 
            "is_feed_ad": false, 
            "gallary_flag": 2, 
            "behot_time": 1553789401, 
            "comments_count": 13, 
            "group_id": "6654506099221201420", 
            "middle_image": "http://p9.pstatp.com/list/pgc-image/0ce0d5d24e5c459ca838f5874a02f5e2"
        }, 
        {
            "image_url": "//p9.pstatp.com/list/pgc-image/RLynZlVImyt0Iq", 
            "single_mode": false, 
            "middle_mode": true, 
            "more_mode": true, 
            "tag": "news_society", 
            "chinese_tag": "社会", 
            "tag_url": "news_society", 
            "title": "胆真肥！成都一业主深夜挖墙开洞，自建车库让邻居心惊胆战", 
            "label": [
                "成都商报", 
                "成都", 
                "新能源", 
                "新能源汽车"
            ], 
            "source": "图说城事儿", 
            "group_source": 2, 
            "has_gallery": true, 
            "media_url": "/c/user/5739097906/", 
            "media_avatar_url": "//p3.pstatp.com/large/9301/1246877109", 
            "image_list": [
                {
                    "url": "//p9.pstatp.com/list/190x124/pgc-image/RLynZlVImyt0Iq"
                }, 
                {
                    "url": "//p3.pstatp.com/list/190x124/pgc-image/RLynZmd9iR7CYq"
                }, 
                {
                    "url": "//p3.pstatp.com/list/190x124/pgc-image/RLynZmq68LxFyM"
                }, 
                {
                    "url": "//p1.pstatp.com/list/190x124/pgc-image/RLynZn4F7AyTiJ"
                }
            ], 
            "gallary_image_count": 4, 
            "source_url": "/group/6673277718819242500/", 
            "article_genre": "gallery", 
            "item_id": "6673277718819242500", 
            "is_feed_ad": false, 
            "gallary_flag": 2, 
            "behot_time": 1553789400, 
            "comments_count": 8, 
            "group_id": "6673277718819242500", 
            "middle_image": "http://p9.pstatp.com/list/pgc-image/RLynZlVImyt0Iq"
        }, 
        {
            "image_url": "//p1.pstatp.com/list/pgc-image/a1b0f3e6c3a04f2eb535d0eb6f580d2e", 
            "single_mode": false, 
            "middle_mode": true, 
            "more_mode": true, 
            "tag": "news", 
            "chinese_tag": "其它", 
            "tag_url": "search/?keyword=%E5%85%B6%E5%AE%83", 
            "title": "受兰新客专张家庄隧道地质灾害影响，所有动车改走普速铁路", 
            "label": [
                "地质", 
                "西安", 
                "摄影", 
                "西宁"
            ], 
            "source": "铁路心视界", 
            "group_source": 2, 
            "has_gallery": true, 
            "media_url": "/c/user/15043628118/", 
            "media_avatar_url": "//p8.pstatp.com/large/2c69000a82e51ed6a83c", 
            "image_list": [
                {
                    "url": "//p1.pstatp.com/list/190x124/pgc-image/a1b0f3e6c3a04f2eb535d0eb6f580d2e"
                }, 
                {
                    "url": "//p1.pstatp.com/list/190x124/pgc-image/55348638eb0a48e288cd6fc6aa62da5a"
                }, 
                {
                    "url": "//p1.pstatp.com/list/190x124/pgc-image/df16a2c352f1442eb942aa0e541d9ec2"
                }, 
                {
                    "url": "//p3.pstatp.com/list/190x124/pgc-image/578038681b2944df8bad938c70ffa955"
                }
            ], 
            "gallary_image_count": 7, 
            "source_url": "/group/6645858480362095108/", 
            "article_genre": "gallery", 
            "item_id": "6645858480362095108", 
            "is_feed_ad": false, 
            "gallary_flag": 2, 
            "behot_time": 1553789398, 
            "comments_count": 444, 
            "group_id": "6645858480362095108", 
            "middle_image": "http://p1.pstatp.com/list/pgc-image/a1b0f3e6c3a04f2eb535d0eb6f580d2e"
        }, 
        {
            "image_url": "//p1.pstatp.com/list/pgc-image/1bb445fb78d646acbea2997fe2615a6e", 
            "single_mode": false, 
            "middle_mode": true, 
            "more_mode": true, 
            "tag": "news_military", 
            "chinese_tag": "军事", 
            "tag_url": "news_military", 
            "title": "揭秘武警舌尖上的“魔鬼周” 特战队员就地取材吃烧烤", 
            "label": [
                "烧烤", 
                "美食", 
                "视觉中国", 
                "压缩饼干", 
                "炒饭", 
                "酱油", 
                "腌菜", 
                "酱油炒饭", 
                "萱草"
            ], 
            "source": "中国故事工作室", 
            "group_source": 2, 
            "has_gallery": true, 
            "media_url": "/c/user/4218815026/", 
            "media_avatar_url": "//p2.pstatp.com/large/6eeb0001f74b79118b75", 
            "image_list": [
                {
                    "url": "//p1.pstatp.com/list/190x124/pgc-image/1bb445fb78d646acbea2997fe2615a6e"
                }, 
                {
                    "url": "//p1.pstatp.com/list/190x124/pgc-image/89cf9fc35f1f4329a8a39d00606e472a"
                }, 
                {
                    "url": "//p3.pstatp.com/list/190x124/pgc-image/e57b95546f1542f2adb22a62df74e8f8"
                }, 
                {
                    "url": "//p9.pstatp.com/list/190x124/pgc-image/0584fb62fbc94c9199e87d536d50a72c"
                }
            ], 
            "gallary_image_count": 6, 
            "source_url": "/group/6673325595809546765/", 
            "article_genre": "gallery", 
            "item_id": "6673325595809546765", 
            "is_feed_ad": false, 
            "gallary_flag": 3, 
            "behot_time": 1553789397, 
            "comments_count": 15, 
            "group_id": "6673325595809546765", 
            "middle_image": "http://p1.pstatp.com/list/pgc-image/1bb445fb78d646acbea2997fe2615a6e"
        }
    ], 
    "next": {
        "max_behot_time": 1553789397
    }
}